QNPI_InRealisticWaveguides/__init__.py
QNPI_InRealisticWaveguides/classes.py
qnpi_inrealisticwaveguides-0.1.4.dist-info/licenses/LICENSE.txt
qnpi_inrealisticwaveguides-0.1.4.dist-info/METADATA
qnpi_inrealisticwaveguides-0.1.4.dist-info/WHEEL
qnpi_inrealisticwaveguides-0.1.4.dist-info/top_level.txt
qnpi_inrealisticwaveguides-0.1.4.dist-info/RECORD
