Metadata-Version: 2.4
Name: QNPI-InRealisticWaveguides
Version: 0.1.4
Summary: Quantum nonlinear parametric interaction in realistic waveguides
Author-email: Tim Weiss <timweiss001@gmail.com>
License: MIT
Project-URL: Homepage, https://github.com/TimFWeiss/QNPI-InRealisticWaveguides
Project-URL: Bug Tracker, https://github.com/TimFWeiss/QNPI-InRealisticWaveguides/issues
Requires-Python: >=3.9
License-File: LICENSE.txt
Requires-Dist: numpy>=1.25.0
Requires-Dist: scipy>=1.12.1
Requires-Dist: matplotlib>=3.6.3
Requires-Dist: tqdm>=4.66.0
Dynamic: license-file
